dukes/__init__.py
dukes/constant.py
dukes/dukesMain.py
dukes/galDensity.py
dukes/galMassFunction.py
dukes/sysmsg.py
dukes/utils.py
dukes/dat/__init__.py
dukes/dat/cosmicAgeFit.py
dukes/dat/densityParamFit.py
dukes/dat/galacticAreaDensityFit.py
dukes-1.4.0.dist-info/LICENSE
dukes-1.4.0.dist-info/METADATA
dukes-1.4.0.dist-info/WHEEL
dukes-1.4.0.dist-info/top_level.txt
dukes-1.4.0.dist-info/RECORD
