Metadata-Version: 2.1
Name: dukes
Version: 1.4.0
Summary: This package evaluates the signatures of diffuse boosted dark matter by supernova neutrinos in the early Universe
Author-email: Yen-Hsun Lin <yenhsun@phys.ncku.edu.tw>
License: GNU GENERAL PUBLIC LICENSE
Project-URL: Homepage, https://github.com/yenhsunlin/dukes
Requires-Python: >=3.8
License-File: LICENSE
Requires-Dist: numpy >=1.20.0
Requires-Dist: scipy >=1.10.0
Requires-Dist: vegas >=6.0.1
